creds_vault-1.0.3.dist-info/licenses/LICENSE
secrets_cli/__init__.py
secrets_cli/cli.py
creds_vault-1.0.3.dist-info/METADATA
creds_vault-1.0.3.dist-info/WHEEL
creds_vault-1.0.3.dist-info/entry_points.txt
creds_vault-1.0.3.dist-info/top_level.txt
creds_vault-1.0.3.dist-info/RECORD
