Metadata-Version: 2.4
Name: creds-vault
Version: 1.0.3
Summary: Secure environment variable synchronization tool
Author-email: Mudassir Mirza <hello.mudassirmirza@gmail.com>
Maintainer-email: Mudassir Mirza <hello.mudassirmirza@gmail.com>
License: MIT
Project-URL: Homepage, https://github.com/mirzamudassir/secrets-cli
Project-URL: Documentation, https://github.com/mirzamudassir/secrets-cli#readme
Project-URL: Repository, https://github.com/mirzamudassir/secrets-cli
Project-URL: Bug Reports, https://github.com/mirzamudassir/secrets-cli/issues
Project-URL: Changelog, https://github.com/mirzamudassir/secrets-cli/blob/main/CHANGELOG.md
Keywords: secrets-cli,environment,dotenv,encryption,cli,github,gist,security,devops
Classifier: Development Status :: 5 - Production/Stable
Classifier: Intended Audience :: Developers
Classifier: License :: OSI Approved :: MIT License
Classifier: Operating System :: OS Independent
Classifier: Programming Language :: Python :: 3
Classifier: Programming Language :: Python :: 3.7
Classifier: Programming Language :: Python :: 3.8
Classifier: Programming Language :: Python :: 3.9
Classifier: Programming Language :: Python :: 3.10
Classifier: Programming Language :: Python :: 3.11
Classifier: Topic :: Security :: Cryptography
Classifier: Topic :: Software Development :: Libraries :: Python Modules
Classifier: Topic :: System :: Systems Administration
Classifier: Topic :: Utilities
Requires-Python: >=3.7
License-File: LICENSE
Requires-Dist: requests>=2.25.0
Requires-Dist: cryptography>=3.0.0
Provides-Extra: dev
Requires-Dist: pytest>=6.0; extra == "dev"
Requires-Dist: pytest-cov>=2.10; extra == "dev"
Requires-Dist: black>=21.0; extra == "dev"
Requires-Dist: flake8>=3.8; extra == "dev"
Requires-Dist: mypy>=0.800; extra == "dev"
Requires-Dist: twine>=3.0; extra == "dev"
Requires-Dist: pip-audit>=2.0; extra == "dev"
Requires-Dist: safety>=2.0; extra == "dev"
Dynamic: license-file
